LICENSE
README.md
setup.cfg
setup.py
miso/__init__.py
miso/sdk.py
miso/version.py
miso/api/__init__.py
miso/api/base.py
miso/api/bulk.py
miso/api/experiment.py
miso/api/interaction.py
miso/api/product.py
miso/api/qa.py
miso/api/recommendation.py
miso/api/search.py
miso/api/user.py
miso_sdk.egg-info/PKG-INFO
miso_sdk.egg-info/SOURCES.txt
miso_sdk.egg-info/dependency_links.txt
miso_sdk.egg-info/requires.txt
miso_sdk.egg-info/top_level.txt
tests/__init__.py
tests/test_payload_validation.py
tests/utils.py
tests/api/__init__.py
tests/api/test_api_call.py
tests/api/test_api_params.py