Metadata-Version: 2.1
Name: miso-sdk
Version: 1.3.0
Summary: Enhance your site with high conversion magic with Miso's power.
Home-page: https://github.com/MisoAI/miso-python-sdk
License: MIT
Project-URL: Miso, https://askmiso.com/
Project-URL: Miso Document, https://docs.askmiso.com/
Project-URL: Miso API Document, https://api.askmiso.com/
Classifier: Development Status :: 4 - Beta
Classifier: Intended Audience :: Developers
Classifier: Topic :: Software Development :: Build Tools
Classifier: License :: OSI Approved :: MIT License
Classifier: Programming Language :: Python :: 3
Classifier: Programming Language :: Python :: 3.7
Classifier: Programming Language :: Python :: 3.8
Classifier: Programming Language :: Python :: 3.9
Classifier: Programming Language :: Python :: 3.10
Classifier: Programming Language :: Python :: 3.11
Requires-Python: >=3.7, <4
License-File: LICENSE
